palworld_admin/__init__.py
palworld_admin/classes/__init__.py
palworld_admin/classes/dbmodels.py
palworld_admin/classes/discord_client.py
palworld_admin/classes/localserver.py
palworld_admin/classes/memorystorage.py
palworld_admin/classes/palworldsettings.py
palworld_admin/converter/convert.py
palworld_admin/converter/lib/__init__.py
palworld_admin/converter/lib/archive.py
palworld_admin/converter/lib/gvas.py
palworld_admin/converter/lib/noindent.py
palworld_admin/converter/lib/palsav.py
palworld_admin/converter/lib/paltypes.py
palworld_admin/converter/lib/rawdata/__init__.py
palworld_admin/converter/lib/rawdata/base_camp.py
palworld_admin/converter/lib/rawdata/base_camp_module.py
palworld_admin/converter/lib/rawdata/build_process.py
palworld_admin/converter/lib/rawdata/character.py
palworld_admin/converter/lib/rawdata/character_container.py
palworld_admin/converter/lib/rawdata/connector.py
palworld_admin/converter/lib/rawdata/debug.py
palworld_admin/converter/lib/rawdata/dynamic_item.py
palworld_admin/converter/lib/rawdata/foliage_model.py
palworld_admin/converter/lib/rawdata/foliage_model_instance.py
palworld_admin/converter/lib/rawdata/group.py
palworld_admin/converter/lib/rawdata/item_container.py
palworld_admin/converter/lib/rawdata/item_container_slots.py
palworld_admin/converter/lib/rawdata/map_concrete_model.py
palworld_admin/converter/lib/rawdata/map_model.py
palworld_admin/converter/lib/rawdata/work_collection.py
palworld_admin/converter/lib/rawdata/worker_director.py
palworld_admin/helper/__init__.py
palworld_admin/helper/cli.py
palworld_admin/helper/consolemanagement.py
palworld_admin/helper/dbcreation.py
palworld_admin/helper/dbmanagement.py
palworld_admin/helper/dbmigration.py
palworld_admin/helper/fileprocessing.py
palworld_admin/helper/networking.py
palworld_admin/helper/oscommands.py
palworld_admin/helper/threads.py
palworld_admin/icon.png
palworld_admin/main.py
palworld_admin/migrations/alembic.ini
palworld_admin/migrations/env.py
palworld_admin-0.10.4.dist-info/entry_points.txt
palworld_admin-0.10.4.dist-info/METADATA
palworld_admin-0.10.4.dist-info/WHEEL
palworld_admin-0.10.4.dist-info/RECORD
