Metadata-Version: 2.1
Name: palworld_admin
Version: 0.10.4
Summary: Palworld Admin is a GUI to manage your Palworld Dedicated Server, including deployment, configuration, monitoring and backups.
License: Expressed Permission Only
Author: Lukium
Author-email: mrlukium@outlook.com
Requires-Python: >=3.11,<3.13
Classifier: License :: Other/Proprietary License
Classifier: Programming Language :: Python :: 3
Classifier: Programming Language :: Python :: 3.11
Classifier: Programming Language :: Python :: 3.12
Requires-Dist: Flask (>=3.0.1,<4.0.0)
Requires-Dist: cryptography (>=42.0.2)
Requires-Dist: discord (>=2.3.2,<3.0.0)
Requires-Dist: eventlet (>=0.35.1,<0.36.0)
Requires-Dist: flask-migrate (>=4.0.5,<5.0.0)
Requires-Dist: flask-openid-steam (>=1.3.1,<2.0.0)
Requires-Dist: flask-socketio (>=5.3.6,<6.0.0)
Requires-Dist: flask-sqlalchemy (>=3.1.1,<4.0.0)
Requires-Dist: requests (>=2.31.0,<3.0.0)
